bugcam/__init__.py
bugcam/cli.py
bugcam/commands/__init__.py
bugcam/commands/autostart.py
bugcam/commands/detect.py
bugcam/commands/models.py
bugcam/commands/preview.py
bugcam/commands/record.py
bugcam/commands/setup.py
bugcam/commands/status.py
bugcam/config.py
bugcam/detection_handler.py
bugcam/pipelines/__init__.py
bugcam/pipelines/detection.py
bugcam/pipelines/detection_simple.py
bugcam/utils.py
bugcam-0.1.32.dist-info/LICENSE
bugcam-0.1.32.dist-info/METADATA
bugcam-0.1.32.dist-info/WHEEL
bugcam-0.1.32.dist-info/entry_points.txt
bugcam-0.1.32.dist-info/RECORD
