Metadata-Version: 2.3
Name: bugcam
Version: 0.1.32
Summary: detect and classify insects on a raspberry pi
License: MIT
Keywords: hailo,raspberry-pi,insect-detection,insect-classification,computer-vision,ai,sensing-garden,mit,senseable-city-lab
Author: Deniz Aydemir
Author-email: deniz@aydemir.us
Requires-Python: >=3.11,<4.0
Classifier: Development Status :: 3 - Alpha
Classifier: Intended Audience :: Developers
Classifier: Intended Audience :: Science/Research
Classifier: License :: OSI Approved :: MIT License
Classifier: Programming Language :: Python :: 3
Classifier: Programming Language :: Python :: 3.11
Classifier: Programming Language :: Python :: 3.12
Classifier: Programming Language :: Python :: 3.13
Classifier: Topic :: Multimedia :: Video
Classifier: Topic :: Scientific/Engineering :: Artificial Intelligence
Requires-Dist: boto3 (>=1.34.0)
Requires-Dist: numpy (<2.0.0)
Requires-Dist: opencv-python
Requires-Dist: rich (>=13.0.0)
Requires-Dist: sensing-garden-client (>=0.0.8)
Requires-Dist: setproctitle
Requires-Dist: typer[all] (>=0.9.0)
Project-URL: Repository, https://github.com/MIT-Senseable-City-Lab/sensing-garden
